Workbook

Sheet main
I2: Price | J2: 34.37
I3: Shares | J3: 294.4 | K3: Q125
I4: MC | J4: =J2*J3 -> 10118.528
I5: Cash | J5: 1731.9 | K5: Q125
I6: Debt | J6: =141.7+13225.3 -> 13367 | K6: Q125
I7: EV | J7: =J4+J6-J5 -> 21753.628
I9: debt to cash | J9: =J6/J5 -> 7.7181131
I11: fcf to mc | J11: =J4/Sheet1!L20 -> 11.053668
I12: pe | J12: =J4/Sheet1!L13 -> 9.504535
I13: price to sales | J13: =J4/Sheet1!L2 -> 0.58690456

Sheet Sheet1
A1: main | C1: Q124 | D1: Q224 | E1: Q324 | F1: Q424 | G1: Q125 | L1: 2024 | M1: =L1+1 -> 2025 | N1: =M1+1 -> 2026 | O1: =N1+1 -> 2027 | P1: =O1+1 -> 2028 | Q1: =P1+1 -> 2029 | R1: =Q1+1 -> 2030 | S1: =R1+1 -> 2031 | T1: =S1+1 -> 2032 | ... W1: =V1+1 -> 2035
B2: Revenue | C2: 4383.5 | D2: 4327.4 | E2: 4183.1 | F2: 4346.6 | G2: 4277.1 | L2: 17240.5 | M2: =L2*1.03 -> 17757.715 | N2: =M2*1.03 -> 18290.446 | O2: =N2*1.03 -> 18839.16 | P2: =O2*1.01 -> 19027.551 | Q2: =P2*1.01 -> 19217.827 | R2: =Q2*1.01 -> 19410.005 | S2: =R2*1.01 -> 19604.105 | T2: =S2*1.01 -> 19800.146 | U2: =T2*1.01 -> 19998.148 | V2: =U2*1.01 -> 20198.129 | W2: =V2*1.01 -> 20400.111
B3: COGS | C3: 2360.8 | D3: 2323.2 | E3: 2315.2 | F3: 2394.4 | G3: 2319.9 | L3: 9393.5 | M3: =L3*1.04 -> 9769.24 | N3: =M3*1.03 -> 10062.317 | O3: =N3*1.03 -> 10364.187 | P3: =O3*1.012 -> 10488.557 | Q3: =P3*1.012 -> 10614.42 | R3: =Q3*1.012 -> 10741.793 | S3: =R3*1.012 -> 10870.694 | T3: =S3*1.012 -> 11001.143 | U3: =T3*1.012 -> 11133.156 | V3: =U3*1.012 -> 11266.754 | W3: =V3*1.012 -> 11401.955
B4: Gross Profit | C4: =C2-C3 -> 2022.7 | D4: =D2-D3 -> 2004.2 | E4: =E2-E3 -> 1867.9 | F4: =F2-F3 -> 1952.2 | G4: =G2-G3 -> 1957.2 | L4: =L2-L3 -> 7847 | M4: =M2-M3 -> 7988.475 | N4: =N2-N3 -> 8228.1292 | O4: =O2-O3 -> 8474.9731 | P4: =P2-P3 -> 8538.9945 | Q4: =Q2-Q3 -> 8603.4073 | R4: =R2-R3 -> 8668.2126 | S4: =S2-S3 -> 8733.4111 | ... W4: =W2-W3 -> 8998.1554
B5: SG&A Expense | C5: 1324.3 | D5: 1335 | E5: 1301.8 | F5: 1384.3 | G5: 1307.2 | L5: 5345.5 | M5: =L5*1.02 -> 5452.41 | N5: =M5*1.02 -> 5561.4582 | O5: =N5*1.02 -> 5672.6874 | P5: 5672.6874 | Q5: 5672.6874 | R5: 5672.6874 | S5: 5672.6874 | T5: 5672.6874 | U5: 5672.6874 | V5: 5672.6874 | W5: 5672.6874
B6: R&D Expense | C6: 0 | D6: 0 | E6: 0 | F6: 0 | G6: 0 | L6: 0 | M6: 0 | N6: 0 | O6: 0 | P6: 0 | Q6: 0 | R6: 0 | S6: 0 | T6: 0 | U6: 0 | V6: 0 | W6: 0
B7: Other expenses | C7: 240 | D7: 243.5 | E7: 251.3 | F7: 276.3 | G7: 264.9 | L7: 1011 | M7: =L7*1.02 -> 1031.22 | N7: =M7*1.02 -> 1051.8444 | O7: =N7*1.02 -> 1072.8813 | P7: =O7*1.01 -> 1083.6101 | Q7: =P7*1.01 -> 1094.4462 | R7: =Q7*1.01 -> 1105.3907 | S7: =R7*1.01 -> 1116.4446 | T7: =S7*1.01 -> 1127.609 | U7: =T7*1.01 -> 1138.8851 | V7: =U7*1.01 -> 1150.274 | W7: =V7*1.01 -> 1161.7767
B8: Operating Expenses | C8: =SUM(C5:C7) -> 1564.3 | D8: =SUM(D5:D7) -> 1578.5 | E8: =SUM(E5:E7) -> 1553.1 | F8: =SUM(F5:F7) -> 1660.6 | G8: =SUM(G5:G7) -> 1572.1 | L8: =SUM(L5:L7) -> 6356.5 | M8: =SUM(M5:M7) -> 6483.63 | N8: =SUM(N5:N7) -> 6613.3026 | O8: =SUM(O5:O7) -> 6745.5687 | P8: =SUM(P5:P7) -> 6756.2975 | Q8: =SUM(Q5:Q7) -> 6767.1336 | R8: =SUM(R5:R7) -> 6778.078 | S8: =SUM(S5:S7) -> 6789.1319 | ... W8: =SUM(W5:W7) -> 6834.4641
B9: Operating Income | C9: =C4-C8 -> 458.4 | D9: =D4-D8 -> 425.7 | E9: =E4-E8 -> 314.8 | F9: =F4-F8 -> 291.6 | G9: =G4-G8 -> 385.1 | L9: =L4-L8 -> 1490.5 | M9: =M4-M8 -> 1504.845 | N9: =N4-N8 -> 1614.8266 | O9: =O4-O8 -> 1729.4045 | P9: =P4-P8 -> 1782.697 | Q9: =Q4-Q8 -> 1836.2738 | R9: =R4-R8 -> 1890.1345 | S9: =S4-S8 -> 1944.2792 | ... W9: =W4-W8 -> 2163.6914
B10: Other Income | C10: -115 | D10: -154.4 | E10: -18.1 | F10: -85.9 | G10: -118.3 | L10: -373.4 | M10: =-(M2*0.03) -> -532.73145 | N10: =-(N2*0.03) -> -548.71339 | O10: =-(O2*0.03) -> -565.1748 | P10: =-(P2*0.03) -> -570.82654 | Q10: =-(Q2*0.03) -> -576.53481 | R10: =-(R2*0.03) -> -582.30016 | S10: =-(S2*0.03) -> -588.12316 | T10: =-(T2*0.03) -> -594.00439 | ... W10: =-(W2*0.03) -> -612.00332
B11: Pretax Income | C11: =C9+C10 -> 343.4 | D11: =D9+D10 -> 271.3 | E11: =E9+E10 -> 296.7 | F11: =F9+F10 -> 205.7 | G11: =G9+G10 -> 266.8 | L11: =L9+L10 -> 1117.1 | M11: =M9+M10 -> 972.11355 | N11: =N9+N10 -> 1066.1133 | O11: =O9+O10 -> 1164.2297 | P11: =P9+P10 -> 1211.8705 | Q11: =Q9+Q10 -> 1259.7389 | R11: =R9+R10 -> 1307.8344 | S11: =S9+S10 -> 1356.156 | ... W11: =W9+W10 -> 1551.688
B12: Income Taxes | C12: 43.7 | D12: -11.6 | E12: 52.6 | F12: -32.2 | G12: 40.1 | L12: 52.5 | M12: =M11*0.05 -> 48.605678 | N12: =N11*0.05 -> 53.305663 | O12: =O11*0.05 -> 58.211484 | P12: =P11*0.05 -> 60.593524 | Q12: =Q11*0.05 -> 62.986947 | R12: =R11*0.05 -> 65.391718 | S12: =S11*0.05 -> 67.8078 | T12: =T11*0.05 -> 70.235152 | ... W12: =W11*0.05 -> 77.584402
B13: Net Income | C13: =C11-C12 -> 299.7 | D13: =D11-D12 -> 282.9 | E13: =E11-E12 -> 244.1 | F13: =F11-F12 -> 237.9 | G13: =G11-G12 -> 226.7 | L13: =L11-L12 -> 1064.6 | M13: =M11-M12 -> 923.50787 | N13: =N11-N12 -> 1012.8076 | O13: =O11-O12 -> 1106.0182 | P13: =P11-P12 -> 1151.277 | Q13: =Q11-Q12 -> 1196.752 | R13: =R11-R12 -> 1242.4426 | S13: =S11-S12 -> 1288.3482 | ... W13: =W11-W12 -> 1474.1036 | X13: =W13*1.02 -> 1503.5857 | Y13: =X13*1.02 -> 1533.6574 | Z13: =Y13*1.02 -> 1564.3306 | AA13: =Z13*1.02 -> 1595.6172 | AB13: =AA13*1.02 -> 1627.5295 | AC13: =AB13*1.02 -> 1660.0801 | AD13: =AC13*1.02 -> 1693.2817 | AE13: =AD13*1.02 -> 1727.1474 | ... EC13: =EB13*1.02 -> 13018.079
B16: revenue growth | D16: =D2/C2-1 -> -0.012797992 | E16: =E2/D2-1 -> -0.033345658 | F16: =F2/E2-1 -> 0.039085845 | G16: =G2/F2-1 -> -0.015989509
W17: Terminal | X17: 0.02
B18: CFFO | C18: 549.3 | D18: 474.2 | E18: 667.4 | F18: 671.6 | G18: 547.1 | L18: 2362 | W18: Discount | X18: 0.07
B19: CAPEX | C19: =172.1+10.5 -> 182.6 | D19: =238.2+31.2 -> 269.4 | E19: =336.2+254 -> 590.2 | F19: 0 | G19: 0 | L19: =1150.6+296 -> 1446.6 | W19: Roic
B20: FCF | C20: =C18-C19 -> 366.7 | D20: =D18-D19 -> 204.8 | E20: =E18-E19 -> 77.2 | F20: =F18-F19 -> 671.6 | G20: =G18-G19 -> 547.1 | L20: =L18-L19 -> 915.4 | W20: NPV | X20: =NPV(X18,L13:EC13)+main!J5-main!J6 -> 11022.415
W21: Share | X21: =X20/main!J3 -> 37.440267 | Z21: very conservative valuation
Z22: worst case scenario it is fairly valued
