Workbook

Sheet main
P1: without leases
A2: Dry van | B2: 2003 | M2: Price | N2: 18
A3: Reefer | B3: 99 | M3: Shares | N3: 120 | P3: 120M
A4: Other specialized containers | B4: 60 | M4: MC | N4: =N3*N2 -> 2160 | P4: 2160
B5: =SUM(B2:B4) -> 2162 | M5: Cash | N5: 1314 | P5: 1314
M6: Debt | N6: =1321+4600+60+408 -> 6389 | P6: =60+1321 -> 1381
A7: Geo trade zones (percentage of total TEU) | M7: EV | N7: =N4+N6-N5 -> 7235 | P7: =P4+P6-P5 -> 2227
A8: Pacific | B8: 0.43
A9: Cross-Suez | B9: 0.09 | N9: =N4/model!O2 -> 0.25631897 | O9: =N4/model!O16 -> 1.0027855
A10: Atlantic-Europe | B10: 0.15
A11: Intra-asia | B11: 0.2 | M11: how many FCF | N11: =N4/model!O21 -> 0.57569296
A12: Latin Aemrica | B12: 0.13

Sheet model
A1: main | J1: 2019 | K1: 2020 | L1: 2021 | M1: 2022 | N1: 2023 | O1: 2024 | P1: =O1+1 -> 2025 | Q1: =P1+1 -> 2026 | R1: =Q1+1 -> 2027 | S1: =R1+1 -> 2028 | T1: =S1+1 -> 2029 | U1: =T1+1 -> 2030 | V1: =U1+1 -> 2031 | W1: =V1+1 -> 2032 | ... BF1: =BE1+1 -> 2067
B2: Revenue | J2: 3300 | K2: 3992 | L2: 10729 | M2: 12561 | N2: 5162 | O2: 8427 | P2: =O2*0.7 -> 5898.9 | Q2: =P2*1.1 -> 6488.79 | R2: =Q2*1.1 -> 7137.669 | S2: =R2*1.1 -> 7851.4359 | T2: =S2*1.02 -> 8008.4646 | U2: =T2*1.02 -> 8168.6339 | V2: =U2*1.02 -> 8332.0066
B3: Operating expenses | J3: 2811 | K3: 2835 | L3: 3906 | M3: 4764 | N3: 3885 | O3: 4513 | P3: =O3*1.02 -> 4603.26 | Q3: =P3*1.02 -> 4695.3252 | R3: =Q3*1.02 -> 4789.2317 | S3: =R3*1.02 -> 4885.0163 | T3: =S3*1.02 -> 4982.7167 | U3: =T3*1.02 -> 5082.371 | V3: =U3*1.02 -> 5184.0184
B4: Depreciation | J4: 226 | K4: 292 | L4: 756 | M4: 1370 | N4: 1449 | O4: 1130 | P4: =O4*1.02 -> 1152.6 | Q4: =P4*1.02 -> 1175.652 | R4: =Q4*1.02 -> 1199.165 | S4: =R4*1.02 -> 1223.1483 | T4: =S4*1.02 -> 1247.6113 | U4: =T4*1.02 -> 1272.5635 | V4: =U4*1.02 -> 1298.0148
B5: Impairment of assets | J5: 0 | K5: 0 | L5: 0 | M5: 0 | N5: 2034 | O5: 0 | P5: 0 | Q5: 0 | R5: 0 | S5: 0 | T5: 0 | U5: 0 | V5: 0
B6: Gross Profit | J6: =J2-J3-J4-J5 -> 263 | K6: =K2-K3-K4-K5 -> 865 | L6: =L2-L3-L4-L5 -> 6067 | M6: =M2-M3-M4-M5 -> 6427 | N6: =N2-N3-N4-N5 -> -2206 | O6: =O2-O3-O4-O5 -> 2784 | P6: =P2-P3-P4-P5 -> 143.04 | Q6: =Q2-Q3-Q4-Q5 -> 617.8128 | ... V6: =V2-V3-V4-V5 -> 1849.9734
B7: Other operating income | J7: 38 | K7: 13 | L7: 15 | M7: 49 | N7: 14 | O7: 46 | P7: =O7*1.02 -> 46.92 | Q7: 46 | R7: 46 | S7: 46 | T7: 46 | U7: 46 | V7: 46
B8: Other operating expense | J8: 1 | K8: 4 | L8: 1 | M8: 1 | N8: 29 | O8: 1 | P8: 10 | Q8: 10 | R8: 10 | S8: 10 | T8: 10 | U8: 10 | V8: 10
B9: general administrative expenses | J9: 152 | K9: 163 | L9: 268 | M9: 338 | N9: 280 | O9: 296 | P9: =O9*1.03 -> 304.88 | Q9: =P9*1.03 -> 314.0264 | R9: =Q9*1.03 -> 323.44719 | S9: =R9*1.03 -> 333.15061 | T9: =S9*1.03 -> 343.14513 | U9: =T9*1.03 -> 353.43948 | V9: =U9*1.03 -> 364.04266
B10: Share of loss of associates | J10: 5 | K10: 3 | L10: 4 | M10: 0 | N10: 7.8 | O10: 6 | P10: 6 | Q10: 6 | R10: 6 | S10: 6 | T10: 6 | U10: 6 | V10: 6
B11: Results from operating activities | J11: =J6+J7-J8-J9-J10 -> 143 | K11: =K6+K7-K8-K9-K10 -> 708 | L11: =L6+L7-L8-L9-L10 -> 5809 | M11: =M6+M7-M8-M9-M10 -> 6137 | N11: =N6+N7-N8-N9-N10 -> -2508.8 | O11: =O6+O7-O8-O9-O10 -> 2527 | P11: =P6+P7-P8-P9-P10 -> -130.92 | Q11: =Q6+Q7-Q8-Q9-Q10 -> 333.7864 | ... V11: =V6+V7-V8-V9-V10 -> 1515.9307
B12: Finance income | J12: 2 | K12: 8 | L12: 19 | M12: 131 | N12: 142 | O12: 149 | P12: =O12*1.02 -> 151.98 | Q12: =P12*1.02 -> 155.0196 | R12: =Q12*1.02 -> 158.11999 | S12: =R12*1.02 -> 161.28239 | T12: =S12*1.02 -> 164.50804 | U12: =T12*1.02 -> 167.7982 | V12: =U12*1.02 -> 171.15416
B13: Finance expense | J13: 157 | K13: 189 | L13: 175 | M13: 240 | N13: 446 | O13: 471 | P13: =O13*1.03 -> 485.13 | Q13: =P13*1.03 -> 499.6839 | R13: =Q13*1.03 -> 514.67442 | S13: =R13*1.03 -> 530.11465 | T13: =S13*1.03 -> 546.01809 | U13: =T13*1.03 -> 562.39863 | V13: =U13*1.03 -> 579.27059
B14: Profit before income taxes | J14: =J11+J12-J13 -> -12 | K14: =K11+K12-K13 -> 527 | L14: =L11+L12-L13 -> 5653 | M14: =M11+M12-M13 -> 6028 | N14: =N11+N12-N13 -> -2812.8 | O14: =O11+O12-O13 -> 2205 | P14: =P11+P12-P13 -> -464.07 | Q14: =Q11+Q12-Q13 -> -10.8779 | ... V14: =V11+V12-V13 -> 1107.8143
B15: Income taxes | J15: 12 | K15: 17 | L15: 1010 | M15: 1398 | N15: -127 | O15: 51 | P15: =P14*0.12 -> -55.6884 | Q15: =Q14*0.12 -> -1.305348 | R15: =R14*0.12 -> 59.912477 | S15: =S14*0.12 -> 128.5546 | T15: =T14*0.12 -> 130.01778 | U15: =U14*0.12 -> 131.47914 | V15: =V14*0.12 -> 132.93771
B16: Net income | J16: =J14-J15 -> -24 | K16: =K14-K15 -> 510 | L16: =L14-L15 -> 4643 | M16: =M14-M15 -> 4630 | N16: =N14-N15 -> -2685.8 | O16: =O14-O15 -> 2154 | P16: =P14-P15 -> -408.3816 | Q16: =Q14-Q15 -> -9.572552 | ... V16: =V14-V15 -> 974.87656 | W16: =V16*1.02 -> 994.37409 | X16: =W16*1.02 -> 1014.2616 | Y16: =X16*1.02 -> 1034.5468 | Z16: =Y16*1.02 -> 1055.2377 | AA16: =Z16*1.02 -> 1076.3425 | AB16: =AA16*1.02 -> 1097.8693 | AC16: =AB16*1.02 -> 1119.8267 | AD16: =AC16*1.02 -> 1142.2233 | ... CH16: =CG16*1.02 -> 3462.2675
B18: revenue y/y | K18: =K2/J2-1 -> 0.20969697 | L18: =L2/K2-1 -> 1.6876253 | M18: =M2/L2-1 -> 0.17075217 | N18: =N2/M2-1 -> -0.58904546 | O18: =O2/N2-1 -> 0.63250678 | P18: =P2/O2-1 -> -0.3 | Q18: =Q2/P2-1 -> 0.1 | R18: =R2/Q2-1 -> 0.1 | ... V18: =V2/U2-1 -> 0.02
B19: net income y/y | K19: =K16/J16-1 -> -22.25 | L19: =L16/K16-1 -> 8.1039216 | M19: =M16/L16-1 -> -0.0027999138 | N19: =N16/M16-1 -> -1.5800864 | O19: =O16/N16-1 -> -1.8019957 | Y19: Terminal | Z19: 0.02
B20: CFO | J20: 370 | K20: 880 | L20: 5970 | M20: 6110 | N20: 1020 | O20: 3752 | Y20: Discount | Z20: 0.08
B21: FCF? | J21: =J20-16 -> 354 | K21: =K20-43 -> 837 | L21: =L20-1005 -> 4965 | M21: =M20-0 -> 6110 | N21: =N20-0 -> 1020 | O21: =O20-0 -> 3752 | Y21: ROIC | Z21: ?
Y22: NPV | Z22: =NPV(Z20,P16:CH16)+main!N5-main!N6 -> 6826.5443
B23: cashflow y/y | K23: =K21/J21-1 -> 1.3644068 | L23: =L21/K21-1 -> 4.9318996 | M23: =M21/L21-1 -> 0.2306143 | N23: =N21/M21-1 -> -0.83306056 | O23: =O21/N21-1 -> 2.6784314 | Y23: Share | Z23: =Z22/main!N3 -> 56.887869
J25: =J15/J14 -> -1 | K25: =K15/K14 -> 0.032258065 | L25: =L15/L14 -> 0.17866619 | M25: =M15/M14 -> 0.23191772 | N25: =N15/N14 -> 0.045150739 | O25: =O15/O14 -> 0.023129252
