Workbook

Sheet main
B2: 45873
B3: Focuses on the development and operation of sustainable | K3: Price | L3: 50
B4: infastructure, through the integration of Toll Roads, Airports, | K4: Shares | L4: 721.8
B5: Consutrciton and Energy. | K5: MC | L5: =L4*L3 -> 36090 | M5: USD | N5: =L5*P6 -> 34738.666 | O5: EUR | P5: 1 | Q5: 1.0389
K6: Cash | L6: 4828 | M6: EUR | P6: =P5/Q5 -> 0.96255655
B7: Cintra manages toll roads | K7: Debt | L7: =10092+165+1196+80 -> 11533 | M7: EUR
B8: Ferrovial Airports | K8: EV | L8: =N5-L6+L7 -> 41443.666
C9: 49% terminal 1 JFK
C10: 60% stake in Dalaman
C11: 5.25% UK Heathrow | K11: price to sales | L11: =N5/model!V7 -> 3.7974055
C12: 50% Glasbow, Aberdeen, and Southampton | K12: price to FCF | L12: =N5/model!V31 -> 39.430949
B13: Energy | K13: price to ni | L13: =L5/model!V20 -> 10.340974
C14: El Berrocal, Spain
K15: we need to see at least 600 in ni for next quarter

Sheet model
E1: 2Q23 | F1: 3Q24 | G1: 3Q23 | H1: 1Q24 | I1: 2Q24 | J1: 3Q24 | K1: 4Q24 | L1: 1Q2025 | M1: 2Q2025 | Q1: 2019 | R1: 2020 | S1: 2021 | T1: 2022 | U1: 2023 | V1: 2024 | W1: =V1+1 -> 2025 | X1: =W1+1 -> 2026 | Y1: =X1+1 -> 2027 | Z1: =Y1+1 -> 2028 | AA1: =Z1+1 -> 2029 | AB1: =AA1+1 -> 2030 | AC1: =AB1+1 -> 2031 | AD1: =AC1+1 -> 2032 | ... DH1: =DG1+1 -> 2114
B2: Highways | E2: 269 | H2: 277 | I2: 318 | L2: 324 | M2: 352
B3: Airports | E3: 23 | H3: 5 | I3: 25 | L3: 5 | M3: 32
B4: Construction | E4: 1714 | H4: 1476 | I4: 1895 | L4: 1584 | M4: 1869
B5: Energy | E5: 54 | H5: 53 | I5: 61 | L5: 74 | M5: 68
B6: Other | E6: 74 | H6: 70 | I6: 87 | L6: 72 | M6: 89
B7: Revenue | E7: 2135 | H7: =SUM(H2:H6) -> 1881 | I7: =SUM(I2:I6) -> 2386 | L7: =SUM(L2:L6) -> 2059 | M7: =SUM(M2:M6) -> 2410 | R7: 6532 | S7: 6778 | T7: =7551+2 -> 7553 | U7: =8514+1 -> 8515 | V7: =9147+1 -> 9148 | W7: =V7*1.08 -> 9879.84 | X7: =W7*1.08 -> 10670.227 | Y7: =X7*1.08 -> 11523.845 | Z7: =Y7*1.08 -> 12445.753 | AA7: =Z7*1.08 -> 13441.413 | AB7: =AA7*1.08 -> 14516.726 | AC7: =AB7*1.02 -> 14807.061 | AD7: =AC7*1.02 -> 15103.202 | AE7: =AD7*1.02 -> 15405.266 | AF7: =AE7*1.02 -> 15713.371 | AG7: =AF7*1.02 -> 16027.639 | AH7: =AG7*1.02 -> 16348.192 | AI7: =AH7*1.02 -> 16675.155 | AJ7: =AI7*1.02 -> 17008.659 | ... DH7: =DG7*1.02 -> 76609.586
B8: Operating expenses | S8: 596 | T8: =1197+4182+1446 -> 6825 | U8: =1047+4878+1599 -> 7524 | V8: =1115+4931+1760 -> 7806
B9: Fixed asset depreciation | T9: 299 | U9: 401 | V9: 441
B10: Impariement and disposal of fixed assets | T10: -6 | U10: 35 | V10: 2208 | X10: check note 2.3 I nfinancial report for large impairment
B11: Operating profit | E11: 106 | H11: 152 | I11: 399 | L11: 496 | M11: 211 | R11: 189 | S11: 1476 | T11: =T7-T8-T9+T10 -> 423 | U11: =U7-U8-U9+U10 -> 625 | V11: =V7-V8-V9+V10 -> 3109
B12: Net financial income from infrastructure projects | T12: -365 | U12: -372 | V12: -411
B13: Net financial income from ex-infrastructure projects | T13: 45 | U13: 188 | V13: 685
B14: Net financial income | R14: -243 | S14: -334 | T14: =T12+T13 -> -320 | U14: =U12+U13 -> -184 | V14: =V12+V13 -> 274
B15: Share of profits of equity accounted companies | T15: 165 | U15: 215 | V15: 238
B16: Profit (loss) before tax | E16: 105 | I16: 404 | L16: 309 | M16: 241 | R16: -427 | S16: 964 | T16: =T11+T14+T15 -> 268 | U16: =U11+U14+U15 -> 656 | V16: =V11+V14+V15 -> 3621
B17: Intome\(expense) tax | T17: -30 | U17: -42 | V17: -145
B18: After tax profit | T18: =SUM(T16:T17) -> 238 | U18: =SUM(U16:U17) -> 614 | V18: =SUM(V16:V17) -> 3476
B19: discontinued operations | L19: =L16*0.07 -> 21.63 | T19: 64 | U19: 16 | V19: 14
B20: Net profit | E20: 85 | I20: 337 | L20: =L16-L19 -> 287.37 | M20: 234 | N20: 600 | O20: 600 | R20: -373 | S20: 1335 | T20: =SUM(T18:T19) -> 302 | U20: =SUM(U18:U19) -> 630 | V20: =SUM(V18:V19) -> 3490 | W20: =V20*0.5 -> 1745 | X20: =W20*1.1 -> 1919.5 | Y20: =X20*1.1 -> 2111.45 | Z20: =Y20*1.05 -> 2217.0225 | AA20: =Z20*1.05 -> 2327.8736 | AB20: =AA20*1.05 -> 2444.2673 | AC20: =AB20*1.05 -> 2566.4807 | AD20: =AC20*1.05 -> 2694.8047 | AE20: =AD20*1.02 -> 2748.7008 | AF20: =AE20*1.02 -> 2803.6748 | AG20: =AF20*1.02 -> 2859.7483 | AH20: =AG20*1.02 -> 2916.9433 | AI20: =AH20*1.02 -> 2975.2821 | AJ20: =AI20*1.02 -> 3034.7878 | AK20: =AJ20*1.02 -> 3095.4835 | AL20: =AK20*1.02 -> 3157.3932 | ... DH20: =DG20*1.02 -> 13669.146
B21: estimated g rate of NI | U21: =U20/T20-1 -> 1.0860927 | V21: =V20/U20-1 -> 4.5396825 | W21: =W20/V20-1 -> -0.5 | X21: =X20/W20-1 -> 0.1 | Y21: =Y20/X20-1 -> 0.1 | Z21: =Z20/Y20-1 -> 0.05 | AA21: =AA20/Z20-1 -> 0.05 | AB21: =AB20/AA20-1 -> 0.05 | ... AU21: =AU20/AT20-1 -> 0.02
Z24: ROIC
B25: revenue y/y | L25: =L7/H7-1 -> 0.094630516 | M25: =M7/I7-1 -> 0.010058676 | S25: =S7/R7-1 -> 0.037660747 | T25: =T7/S7-1 -> 0.11434051 | U25: =U7/T7-1 -> 0.12736661 | V25: =V7/U7-1 -> 0.074339401 | W25: =W7/V7-1 -> 0.08 | X25: =X7/W7-1 -> 0.08 | Y25: =Y7/X7-1 -> 0.08 | Z25: Discount | AA25: 0.07
B26: gross margin | T26: =T11/T7 -> 0.056004237 | U26: =U11/U7 -> 0.073399883 | V26: =V11/V7 -> 0.33985571 | Z26: Terminal | AA26: 0.02
R27: =R20/R7 -> -0.057103491 | S27: =S20/S7 -> 0.19696076 | T27: =T20/T7 -> 0.039984112 | U27: =U20/U7 -> 0.073987082 | V27: =V20/V7 -> 0.38150415 | Z27: NPV | AA27: =NPV(AA25,W20:DH20)+main!L6-main!L7 -> 37835.682
Z28: Share | AA28: =AA27/main!L4 -> 52.418512
B29: CFFO | T29: 1002 | U29: 1263 | V29: 1293 | AA29: 45
B30: CAPEX | T30: =95+809 -> 904 | U30: =319+86 -> 405 | V30: =226+186 -> 412 | AA30: =AA28/AA29-1 -> 0.16485583
B31: FCF | T31: =T29-T30 -> 98 | U31: =U29-U30 -> 858 | V31: =V29-V30 -> 881
B33: CFFO y/y | U33: =U29/T29-1 -> 0.26047904 | V33: =V29/U29-1 -> 0.023752969
B34: FCF y/y | U34: =U31/T31-1 -> 7.755102 | V34: =V31/U31-1 -> 0.026806527
